README.md
setup.py
sr2t/__init__.py
sr2t/__main__.py
sr2t/data/nessus_autoclassify.yaml
sr2t/data/nessus_http.yaml
sr2t/data/nessus_rdp.yaml
sr2t/data/nessus_smb.yaml
sr2t/data/nessus_snmp.yaml
sr2t/data/nessus_ssh.yaml
sr2t/data/nessus_tls.yaml
sr2t/data/nessus_x509.yaml
sr2t/data/testssl.yaml
sr2t/parsers/__init__.py
sr2t/parsers/dirble.py
sr2t/parsers/fortify.py
sr2t/parsers/nessus.py
sr2t/parsers/nikto.py
sr2t/parsers/nmap.py
sr2t/parsers/testssl.py
sr2t_0bs1d1an.egg-info/PKG-INFO
sr2t_0bs1d1an.egg-info/SOURCES.txt
sr2t_0bs1d1an.egg-info/dependency_links.txt
sr2t_0bs1d1an.egg-info/entry_points.txt
sr2t_0bs1d1an.egg-info/requires.txt
sr2t_0bs1d1an.egg-info/top_level.txt