Metadata-Version: 2.1
Name: sr2t-0bs1d1an
Version: 0.0.24
Summary: Converts scanning reports to a tabular format
Home-page: https://gitlab.com/0bs1d1an/sr2t
Author: Guido Kroon (@0bs1d1an)
Author-email: gkroon@maelstrom.ninja
License: UNKNOWN
Project-URL: Bug Reports, https://gitlab.com/0bs1d1an/sr2t/issues
Project-URL: Source, https://gitlab.com/0bs1d1an/sr2t/
Platform: UNKNOWN
Classifier: Development Status :: 3 - Alpha
Classifier: Intended Audience :: Information Technology
Classifier: Intended Audience :: System Administrators
Classifier: Topic :: Security
Classifier: License :: OSI Approved :: GNU General Public License v3 (GPLv3)
Classifier: Operating System :: OS Independent
Classifier: Programming Language :: Python :: 3
Classifier: Programming Language :: Python :: 3.6
Classifier: Programming Language :: Python :: 3.7
Requires-Python: >=3.6
